chemgraph/__init__.py
chemgraph/agent/llm_agent.py
chemgraph/agent/llm_agent_legacy.py
chemgraph/graphs/graspa_agent.py
chemgraph/graphs/mock_agent.py
chemgraph/graphs/multi_agent.py
chemgraph/graphs/python_relp_agent.py
chemgraph/graphs/single_agent.py
chemgraph/models/__init__.py
chemgraph/models/agent_response.py
chemgraph/models/ase_input.py
chemgraph/models/atomsdata.py
chemgraph/models/graspa_input.py
chemgraph/models/multi_agent_response.py
chemgraph/models/supported_models.py
chemgraph/models/calculators/aimnet2_calc.py
chemgraph/models/calculators/emt_calc.py
chemgraph/models/calculators/fairchem_calc.py
chemgraph/models/calculators/mace_calc.py
chemgraph/models/calculators/mopac_calc.py
chemgraph/models/calculators/nwchem_calc.py
chemgraph/models/calculators/orca_calc.py
chemgraph/models/calculators/psi4_calc.py
chemgraph/models/calculators/tblite_calc.py
chemgraph/prompt/claude_prompt.py
chemgraph/prompt/llama_prompt.py
chemgraph/prompt/multi_agent_prompt.py
chemgraph/prompt/qwen_prompt.py
chemgraph/prompt/single_agent_prompt.py
chemgraph/state/multi_agent_state.py
chemgraph/state/state.py
chemgraph/tools/__init__.py
chemgraph/tools/alcf_loader.py
chemgraph/tools/anthropic_loader.py
chemgraph/tools/ase_tools.py
chemgraph/tools/cheminformatics_tools.py
chemgraph/tools/gemini_loader.py
chemgraph/tools/generic_tools.py
chemgraph/tools/graspa_tools.py
chemgraph/tools/groq_loader.py
chemgraph/tools/local_model_loader.py
chemgraph/tools/openai_loader.py
chemgraph/tools/qcengine_tools.py
chemgraph/tools/report_tools.py
chemgraph/tools/files/__init__.py
chemgraph/tools/files/template/__init__.py
chemgraph/utils/__init__.py
chemgraph/utils/get_workflow_from_llm.py
chemgraph/utils/logging_config.py
chemgraph/utils/tool_call_eval.py
chemgraphagent-0.2.1.dist-info/licenses/LICENSE
ui/__init__.py
ui/app.py
ui/cli.py
ui/config.py
chemgraphagent-0.2.1.dist-info/METADATA
chemgraphagent-0.2.1.dist-info/WHEEL
chemgraphagent-0.2.1.dist-info/entry_points.txt
chemgraphagent-0.2.1.dist-info/top_level.txt
chemgraphagent-0.2.1.dist-info/RECORD
